{"data": {"mutexes_created": ["ShimCacheMutex"], "processes_injected": ["dwwin.exe"], "modules_loaded": ["rpcrt4.dll", "shlwapi.dll", "version.dll", "shell32.dll", "advapi32.dll", "ntdll.dll", "kernel32.dll", "c:\\windows\\system32\\dbghelp.dll", "c:\\windows\\system32\\exts.dll", "c:\\windows\\system32\\ntsdexts.dll"], "files_written": ["C:\\Documents and Settings\\All Users\\Application Data\\Microsoft\\Dr Watson\\drwtsn32.log"], "processes_created": ["C:\\WINDOWS\\system32\\drwtsn32 -p 1632 -e 172 -g"], "files_opened": ["C:\\WINDOWS\\system32\\winsock.dll", "C:\\30399ef9aaff0eea7c958a72961858643d440571db008419be45cde55734296e", "\\\\.\\PIPE\\lsarpc", "C:\\WINDOWS\\system32\\winsock.dll", "C:\\WINDOWS\\system32\\drwtsn32.exe", "C:\\Documents and Settings\\All Users\\Application Data\\Microsoft\\Dr Watson\\drwtsn32.log", "C:\\Documents and Settings\\All Users\\Application Data\\Microsoft\\Dr Watson\\drwtsn32.log"]}}