{"data": {"files_copied": [{"source": "C:\\5f3930178ab0228269a67c9dc6db39ba7ef0e43df83b7cac12f9025b2827cbb1", "destination": "C:\\WINDOWS\\mscon"}], "mutexes_created": ["ShimCacheMutex"], "services_created": ["mscon"], "files_written": ["C:\\analyse\\1645050297.901932_4be0117d-29fd-4dcf-9c41-8b46aac88f3d", "C:\\Windows\\UNINSTAL.BAT", "C:\\Windows\\mscon", "C:\\WINDOWS\\bootstat.dat", "C:\\WINDOWS\\UNINSTAL.BAT"], "ip_traffic": [{"transport_layer_protocol": "UDP", "destination_ip": "<MACHINE_DNS_SERVER>", "destination_port": 53}], "dns_lookups": [{"hostname": "www.kmq8.cn"}], "command_executions": ["C:\\Windows\\mscon", "cmd /c C:\\Windows\\UNINSTAL.BAT", " ", "\\??\\C:\\Windows\\system32\\conhost.exe"], "files_deleted": ["C:\\Windows\\UNINSTAL.BAT", "C:\\analyse\\1645050297.901932_4be0117d-29fd-4dcf-9c41-8b46aac88f3d", "C:\\5f3930178ab0228269a67c9dc6db39ba7ef0e43df83b7cac12f9025b2827cbb1", "C:\\WINDOWS\\UNINSTAL.BAT"], "services_opened": ["mscon", "mscon"], "processes_created": ["C:\\Windows\\System32\\cmd.exe", "C:\\WINDOWS\\UNINSTAL.BAT"], "files_opened": ["C:\\Windows\\UNINSTAL.BAT", "C:\\Windows\\mscon", "\\??\\MountPointManager", "\\SystemRoot\\AppPatch\\sysmain.sdb", "C:\\", "C:\\WINDOWS\\bootstat.dat", "C:\\5f3930178ab0228269a67c9dc6db39ba7ef0e43df83b7cac12f9025b2827cbb1", "C:\\WINDOWS\\UNINSTAL.BAT", "\\\\.\\PIPE\\lsarpc", "C:\\WINDOWS\\bootstat.dat", "C:\\5f3930178ab0228269a67c9dc6db39ba7ef0e43df83b7cac12f9025b2827cbb1", "C:\\WINDOWS\\UNINSTAL.BAT", "C:\\WINDOWS\\UNINSTAL.BAT"], "modules_loaded": ["ntdll.dll", "rpcrt4.dll", "advapi32.dll"]}}